ring_doorbell/__init__.py
ring_doorbell/auth.py
ring_doorbell/chime.py
ring_doorbell/cli.py
ring_doorbell/const.py
ring_doorbell/doorbot.py
ring_doorbell/event.py
ring_doorbell/exceptions.py
ring_doorbell/generic.py
ring_doorbell/group.py
ring_doorbell/other.py
ring_doorbell/py.typed
ring_doorbell/ring.py
ring_doorbell/stickup_cam.py
ring_doorbell/util.py
ring_doorbell/webrtcstream.py
ring_doorbell/listen/__init__.py
ring_doorbell/listen/eventlistener.py
ring_doorbell/listen/listenerconfig.py
ring_doorbell-0.9.13.dist-info/METADATA
ring_doorbell-0.9.13.dist-info/WHEEL
ring_doorbell-0.9.13.dist-info/entry_points.txt
ring_doorbell-0.9.13.dist-info/licenses/LICENSE
ring_doorbell-0.9.13.dist-info/RECORD
