Metadata-Version: 2.3
Name: ring-doorbell
Version: 0.9.13
Summary: A Python library to communicate with Ring Door Bell (https://ring.com/)
Project-URL: homepage, https://github.com/python-ring-doorbell/python-ring-doorbell
Project-URL: repository, https://github.com/python-ring-doorbell/python-ring-doorbell
Project-URL: documentation, http://python-ring-doorbell.readthedocs.io/
Project-URL: Bug Tracker, https://github.com/python-ring-doorbell/python-ring-doorbell/issues
Author: python-ring-doorbell developers
License: LGPL-3.0-or-later
Keywords: camera,door bell,home automation,ring
Classifier: Environment :: Other Environment
Classifier: Intended Audience :: Developers
Classifier: License :: OSI Approved :: GNU Lesser General Public License v3 or later (LGPLv3+)
Classifier: Operating System :: OS Independent
Classifier: Programming Language :: Python :: 3
Classifier: Programming Language :: Python :: 3.9
Classifier: Programming Language :: Python :: 3.10
Classifier: Programming Language :: Python :: 3.11
Classifier: Programming Language :: Python :: 3.12
Classifier: Topic :: Home Automation
Classifier: Topic :: Software Development :: Libraries :: Python Modules
Requires-Python: >=3.9.0
Requires-Dist: aiofiles>=23
Requires-Dist: aiohttp>=3
Requires-Dist: async-timeout>=3.0.0
Requires-Dist: asyncclick>=8.1.7.1
Requires-Dist: firebase-messaging>=0.4.0
Requires-Dist: oauthlib<4,>=3.0.0
Requires-Dist: pytz>=2022.0
Requires-Dist: typing-extensions<5.0,>=4.12.2
Requires-Dist: websockets>=13.0.0
Provides-Extra: docs
Requires-Dist: myst-parser; extra == 'docs'
Requires-Dist: sphinx-rtd-theme~=1.3; extra == 'docs'
Requires-Dist: sphinx<7.2.6; extra == 'docs'
